gwcomm/__init__.py
gwcomm/conf.py
gwcomm/filesystem.py
gwcomm/logger.py
gwcomm_genwch-0.0.5.dist-info/LICENSE
gwcomm_genwch-0.0.5.dist-info/METADATA
gwcomm_genwch-0.0.5.dist-info/WHEEL
gwcomm_genwch-0.0.5.dist-info/top_level.txt
gwcomm_genwch-0.0.5.dist-info/RECORD
