Metadata-Version: 2.1
Name: gwcomm-genwch
Version: 0.0.5
Summary: gwcomm
Home-page: https://github.com/genwch/gwcomm
Author: genwch
Author-email: 
License: UNKNOWN
Platform: UNKNOWN
Classifier: Programming Language :: Python :: 3
Classifier: License :: OSI Approved :: MIT License
Classifier: Operating System :: OS Independent
Requires-Python: >=3.7
